odoo/addons/document_page_access_group_user_role/README.rst
odoo/addons/document_page_access_group_user_role/__init__.py
odoo/addons/document_page_access_group_user_role/__manifest__.py
odoo/addons/document_page_access_group_user_role/i18n/document_page_access_group_user_role.pot
odoo/addons/document_page_access_group_user_role/i18n/es.po
odoo/addons/document_page_access_group_user_role/i18n/it.po
odoo/addons/document_page_access_group_user_role/i18n/pt.po
odoo/addons/document_page_access_group_user_role/models/__init__.py
odoo/addons/document_page_access_group_user_role/models/document_page.py
odoo/addons/document_page_access_group_user_role/readme/CONTRIBUTORS.md
odoo/addons/document_page_access_group_user_role/readme/DESCRIPTION.md
odoo/addons/document_page_access_group_user_role/readme/USAGE.md
odoo/addons/document_page_access_group_user_role/static/description/icon.png
odoo/addons/document_page_access_group_user_role/static/description/index.html
odoo/addons/document_page_access_group_user_role/tests/__init__.py
odoo/addons/document_page_access_group_user_role/tests/test_document_page_access_group_user_role.py
odoo/addons/document_page_access_group_user_role/views/document_page_views.xml
odoo_addon_document_page_access_group_user_role-18.0.1.0.0.2.dist-info/METADATA
odoo_addon_document_page_access_group_user_role-18.0.1.0.0.2.dist-info/WHEEL
odoo_addon_document_page_access_group_user_role-18.0.1.0.0.2.dist-info/top_level.txt
odoo_addon_document_page_access_group_user_role-18.0.1.0.0.2.dist-info/RECORD
