Metadata-Version: 2.1
Name: odoo-addon-document_page_access_group_user_role
Version: 18.0.1.0.0.2
Requires-Python: >=3.10
Requires-Dist: odoo-addon-base_user_role==18.0.*
Requires-Dist: odoo-addon-document_page_access_group==18.0.*
Requires-Dist: odoo==18.0.*
Summary: Document Page Access Group User Role
Home-page: https://github.com/OCA/knowledge
License: AGPL-3
Author: Tecnativa, Odoo Community Association (OCA)
Author-email: support@odoo-community.org
Classifier: Programming Language :: Python
Classifier: Framework :: Odoo
Classifier: Framework :: Odoo :: 18.0
Classifier: License :: OSI Approved :: GNU Affero General Public License v3
